MANIFEST.in
README.rst
setup.py
aliyun_python_sdk_lubancloud.egg-info/PKG-INFO
aliyun_python_sdk_lubancloud.egg-info/SOURCES.txt
aliyun_python_sdk_lubancloud.egg-info/dependency_links.txt
aliyun_python_sdk_lubancloud.egg-info/requires.txt
aliyun_python_sdk_lubancloud.egg-info/top_level.txt
aliyunsdklubancloud/__init__.py
aliyunsdklubancloud/request/__init__.py
aliyunsdklubancloud/request/v20180509/BuyOriginPicturesRequest.py
aliyunsdklubancloud/request/v20180509/GetStylesRequest.py
aliyunsdklubancloud/request/v20180509/QueryCutoutTaskResultRequest.py
aliyunsdklubancloud/request/v20180509/QueryGenerateTaskResultRequest.py
aliyunsdklubancloud/request/v20180509/SubmitCutoutTaskRequest.py
aliyunsdklubancloud/request/v20180509/SubmitGenerateTaskRequest.py
aliyunsdklubancloud/request/v20180509/__init__.py